README.md
setup.cfg
setup.py
ifstools/__init__.py
ifstools/ifs.py
ifstools/ifstools.py
ifstools/utils.py
ifstools.egg-info/PKG-INFO
ifstools.egg-info/SOURCES.txt
ifstools.egg-info/dependency_links.txt
ifstools.egg-info/entry_points.txt
ifstools.egg-info/requires.txt
ifstools.egg-info/top_level.txt
ifstools/handlers/AfpFolder.py
ifstools/handlers/GenericFile.py
ifstools/handlers/GenericFolder.py
ifstools/handlers/ImageDecoders.py
ifstools/handlers/ImageFile.py
ifstools/handlers/MD5Folder.py
ifstools/handlers/Node.py
ifstools/handlers/TexFolder.py
ifstools/handlers/__init__.py
ifstools/handlers/lz77.py