Metadata-Version: 1.1
Name: ifstools
Version: 1.13
Summary: Extractor/repacker for Konmai IFS files
Home-page: https://github.com/mon/ifstools/
Author: mon
Author-email: me@mon.im
License: UNKNOWN
Download-URL: https://github.com/mon/ifstools/archive/1.13.tar.gz
Platform: UNKNOWN
